setup.py
powny/__init__.py
powny.egg-info/PKG-INFO
powny.egg-info/SOURCES.txt
powny.egg-info/dependency_links.txt
powny.egg-info/entry_points.txt
powny.egg-info/requires.txt
powny.egg-info/top_level.txt
powny/backends/__init__.py
powny/backends/zookeeper/__init__.py
powny/backends/zookeeper/ifaces.py
powny/backends/zookeeper/zoo.py
powny/core/__init__.py
powny/core/backdoor.py
powny/core/backends.py
powny/core/context.py
powny/core/impscripts.py
powny/core/tools.py
powny/core/api/__init__.py
powny/core/api/cas.py
powny/core/api/jobs.py
powny/core/api/scripts.py
powny/core/api/system.py
powny/core/api/templates/base.html
powny/core/apps/__init__.py
powny/core/apps/api.py
powny/core/apps/collector.py
powny/core/apps/worker.py
powny/core/apps/configs/logging.yaml
powny/core/optconf/__init__.py
powny/core/optconf/converters.py
powny/core/optconf/dumper.py
powny/core/optconf/loader.py
powny/testing/__init__.py
powny/testing/application.py
powny/testing/context.py
powny/testing/tmpfile.py