Metadata-Version: 1.1
Name: powny
Version: 2.9.0
Summary: Distributed events processor, based on stackless technology of PyPy3
Home-page: https://github.com/yandex-sysmon/powny
Author: Devaev Maxim
Author-email: mdevaev@gmail.com
License: GPLv3
Platform: any
Classifier: Development Status :: 4 - Beta
Classifier: License :: OSI Approved :: GNU General Public License v3 (GPLv3)
Classifier: Operating System :: POSIX :: Linux
Classifier: Programming Language :: Python :: 3
Classifier: Programming Language :: Python :: Implementation :: PyPy
Classifier: Topic :: Software Development :: Libraries :: Python Modules
Classifier: Topic :: System :: Distributed Computing
Classifier: Topic :: System :: Networking :: Monitoring
